Metadata-Version: 2.4
Name: modelscope-sam2-fork
Version: 1.0.7
Summary: SAM 2: Segment Anything in Images and Videos
Home-page: https://github.com/facebookresearch/sam2
Author: Meta AI
Author-email: segment-anything@meta.com
License: Apache 2.0
License-File: LICENSE
License-File: LICENSE_cctorch
Requires-Dist: torch
Requires-Dist: torchvision
Requires-Dist: numpy
Requires-Dist: tqdm
Requires-Dist: pillow
Requires-Dist: ms-hydra-core-fork
Dynamic: author
Dynamic: author-email
Dynamic: description
Dynamic: description-content-type
Dynamic: home-page
Dynamic: license
Dynamic: license-file
Dynamic: requires-dist
Dynamic: summary
